provoj/__init__.py
provoj-0.0.0.1.data/scripts/__init__.py
provoj-0.0.0.1.dist-info/DESCRIPTION.rst
provoj-0.0.0.1.dist-info/METADATA
provoj-0.0.0.1.dist-info/RECORD
provoj-0.0.0.1.dist-info/WHEEL
provoj-0.0.0.1.dist-info/metadata.json
provoj-0.0.0.1.dist-info/top_level.txt
