Metadata-Version: 2.0
Name: provoj
Version: 0.0.0.1
Summary: Simple library to test the endpoints of an RESTful API.
Home-page: https://github.com/arnaucode/provoj
Author: arnaucode
Author-email: arnaucode@gmail.com
License: UNKNOWN
Platform: UNKNOWN
